Workbook

Sheet Instructions
B2: SIPlat — System Test Script (UAT)
B3: User Acceptance Test matrix — whole system
B4: Version 1.0 · 14 August 2026
B6: Purpose | C6: A repeatable test script covering every SIPlat portal and the mobile apps. Execute each case, set its Status, and record the actual result. The Summary tab totals results automatically.
B7: How to use | C7: On the 'Test Cases' tab, work top to bottom. For each row: meet the Preconditions, follow the Test Steps, compare against the Expected Result, then set Status and add notes. Put your name and the date in the last columns.
B8: Status values | C8: Not Run (default) · Pass · Fail · Blocked (can't run yet) · N/A (not applicable to this deployment). Use the dropdown in the Status column.
B9: Priority | C9: High = must pass before go-live · Medium = important · Low = nice to have. Prioritise High cases in a time-boxed run.
B10: Type | C10: Functional, Security, Integration, Usability or Negative — indicates what the case is probing.
B11: Test environment | C11: Record the environment (URL / app build) and date of the run here: ____________________________________________
B12: Test accounts | C12: Have one account per role ready: Super Admin, School Administrator, Teacher, Parent, Driver, Transport Manager (plus a suspended account and a custom-role user for RBAC cases).
B13: Defects | C13: For any Fail, log the Test ID, steps, expected vs actual and a screenshot in your defect tracker, and reference it in the Notes column.
B14: Scope note | C14: Covers implemented functionality across web and mobile. The subscription/billing commercial model (Connect/Plus/Complete, entitlement engine, live Stripe) is assessed separately in the Subscription Requirements Validation document and is not exhaustively tested here.

Sheet Summary
B2: Test execution summary
B3: Auto-calculated from the Test Cases tab as you fill in Status.
B5: Overall
B6: Total test cases | C6: =COUNTA('Test Cases'!A2:A119) -> 118
B7: Pass | C7: =COUNTIF('Test Cases'!J2:J119,"Pass") -> 0
B8: Fail | C8: =COUNTIF('Test Cases'!J2:J119,"Fail") -> 0
B9: Blocked | C9: =COUNTIF('Test Cases'!J2:J119,"Blocked") -> 0
B10: N/A | C10: =COUNTIF('Test Cases'!J2:J119,"N/A") -> 0
B11: Not Run | C11: =COUNTIF('Test Cases'!J2:J119,"Not Run") -> 118
B12: Pass rate (of executed) | C12: =IFERROR(COUNTIF('Test Cases'!J2:J119,"Pass")/(COUNTIF('Test Cases'!J2:J119,"Pass")+COUNTIF('Test Cases'!J2:J119,"Fail")),0) -> 0
B14: By area
B15: Area | C15: Total | D15: Pass | E15: Fail | F15: Not Run | G15: Pass %
B16: Authentication & account security | C16: =COUNTIF('Test Cases'!B2:B119,$B16) -> 10 | D16: =COUNTIFS('Test Cases'!B2:B119,$B16,'Test Cases'!J2:J119,"Pass") -> 0 | E16: =COUNTIFS('Test Cases'!B2:B119,$B16,'Test Cases'!J2:J119,"Fail") -> 0 | F16: =COUNTIFS('Test Cases'!B2:B119,$B16,'Test Cases'!J2:J119,"Not Run") -> 10 | G16: =IFERROR(D16/(D16+E16),0) -> 0
B17: Roles & Access Management (item 12) | C17: =COUNTIF('Test Cases'!B2:B119,$B17) -> 8 | D17: =COUNTIFS('Test Cases'!B2:B119,$B17,'Test Cases'!J2:J119,"Pass") -> 0 | E17: =COUNTIFS('Test Cases'!B2:B119,$B17,'Test Cases'!J2:J119,"Fail") -> 0 | F17: =COUNTIFS('Test Cases'!B2:B119,$B17,'Test Cases'!J2:J119,"Not Run") -> 8 | G17: =IFERROR(D17/(D17+E17),0) -> 0
B18: Super Admin — tenants, packages & subscriptions | C18: =COUNTIF('Test Cases'!B2:B119,$B18) -> 7 | D18: =COUNTIFS('Test Cases'!B2:B119,$B18,'Test Cases'!J2:J119,"Pass") -> 0 | E18: =COUNTIFS('Test Cases'!B2:B119,$B18,'Test Cases'!J2:J119,"Fail") -> 0 | F18: =COUNTIFS('Test Cases'!B2:B119,$B18,'Test Cases'!J2:J119,"Not Run") -> 7 | G18: =IFERROR(D18/(D18+E18),0) -> 0
B19: Super Admin — CRM, CMS, content & ops | C19: =COUNTIF('Test Cases'!B2:B119,$B19) -> 8 | D19: =COUNTIFS('Test Cases'!B2:B119,$B19,'Test Cases'!J2:J119,"Pass") -> 0 | E19: =COUNTIFS('Test Cases'!B2:B119,$B19,'Test Cases'!J2:J119,"Fail") -> 0 | F19: =COUNTIFS('Test Cases'!B2:B119,$B19,'Test Cases'!J2:J119,"Not Run") -> 8 | G19: =IFERROR(D19/(D19+E19),0) -> 0
B20: Secure support access (impersonation, item 13) | C20: =COUNTIF('Test Cases'!B2:B119,$B20) -> 4 | D20: =COUNTIFS('Test Cases'!B2:B119,$B20,'Test Cases'!J2:J119,"Pass") -> 0 | E20: =COUNTIFS('Test Cases'!B2:B119,$B20,'Test Cases'!J2:J119,"Fail") -> 0 | F20: =COUNTIFS('Test Cases'!B2:B119,$B20,'Test Cases'!J2:J119,"Not Run") -> 4 | G20: =IFERROR(D20/(D20+E20),0) -> 0
B21: School Admin — people, guardians & import | C21: =COUNTIF('Test Cases'!B2:B119,$B21) -> 6 | D21: =COUNTIFS('Test Cases'!B2:B119,$B21,'Test Cases'!J2:J119,"Pass") -> 0 | E21: =COUNTIFS('Test Cases'!B2:B119,$B21,'Test Cases'!J2:J119,"Fail") -> 0 | F21: =COUNTIFS('Test Cases'!B2:B119,$B21,'Test Cases'!J2:J119,"Not Run") -> 6 | G21: =IFERROR(D21/(D21+E21),0) -> 0
B22: School Admin — calendar, attendance & behaviour | C22: =COUNTIF('Test Cases'!B2:B119,$B22) -> 6 | D22: =COUNTIFS('Test Cases'!B2:B119,$B22,'Test Cases'!J2:J119,"Pass") -> 0 | E22: =COUNTIFS('Test Cases'!B2:B119,$B22,'Test Cases'!J2:J119,"Fail") -> 0 | F22: =COUNTIFS('Test Cases'!B2:B119,$B22,'Test Cases'!J2:J119,"Not Run") -> 6 | G22: =IFERROR(D22/(D22+E22),0) -> 0
B23: School Admin — knowledge, meals & clubs | C23: =COUNTIF('Test Cases'!B2:B119,$B23) -> 5 | D23: =COUNTIFS('Test Cases'!B2:B119,$B23,'Test Cases'!J2:J119,"Pass") -> 0 | E23: =COUNTIFS('Test Cases'!B2:B119,$B23,'Test Cases'!J2:J119,"Fail") -> 0 | F23: =COUNTIFS('Test Cases'!B2:B119,$B23,'Test Cases'!J2:J119,"Not Run") -> 5 | G23: =IFERROR(D23/(D23+E23),0) -> 0
B24: Communications, notifications & messaging | C24: =COUNTIF('Test Cases'!B2:B119,$B24) -> 7 | D24: =COUNTIFS('Test Cases'!B2:B119,$B24,'Test Cases'!J2:J119,"Pass") -> 0 | E24: =COUNTIFS('Test Cases'!B2:B119,$B24,'Test Cases'!J2:J119,"Fail") -> 0 | F24: =COUNTIFS('Test Cases'!B2:B119,$B24,'Test Cases'!J2:J119,"Not Run") -> 7 | G24: =IFERROR(D24/(D24+E24),0) -> 0
B25: Pupil report release (Phase 15) | C25: =COUNTIF('Test Cases'!B2:B119,$B25) -> 5 | D25: =COUNTIFS('Test Cases'!B2:B119,$B25,'Test Cases'!J2:J119,"Pass") -> 0 | E25: =COUNTIFS('Test Cases'!B2:B119,$B25,'Test Cases'!J2:J119,"Fail") -> 0 | F25: =COUNTIFS('Test Cases'!B2:B119,$B25,'Test Cases'!J2:J119,"Not Run") -> 5 | G25: =IFERROR(D25/(D25+E25),0) -> 0
B26: Integrations & Integration Hub | C26: =COUNTIF('Test Cases'!B2:B119,$B26) -> 6 | D26: =COUNTIFS('Test Cases'!B2:B119,$B26,'Test Cases'!J2:J119,"Pass") -> 0 | E26: =COUNTIFS('Test Cases'!B2:B119,$B26,'Test Cases'!J2:J119,"Fail") -> 0 | F26: =COUNTIFS('Test Cases'!B2:B119,$B26,'Test Cases'!J2:J119,"Not Run") -> 6 | G26: =IFERROR(D26/(D26+E26),0) -> 0
B27: Transport manager portal | C27: =COUNTIF('Test Cases'!B2:B119,$B27) -> 6 | D27: =COUNTIFS('Test Cases'!B2:B119,$B27,'Test Cases'!J2:J119,"Pass") -> 0 | E27: =COUNTIFS('Test Cases'!B2:B119,$B27,'Test Cases'!J2:J119,"Fail") -> 0 | F27: =COUNTIFS('Test Cases'!B2:B119,$B27,'Test Cases'!J2:J119,"Not Run") -> 6 | G27: =IFERROR(D27/(D27+E27),0) -> 0
B28: Driver portal & mobile | C28: =COUNTIF('Test Cases'!B2:B119,$B28) -> 5 | D28: =COUNTIFS('Test Cases'!B2:B119,$B28,'Test Cases'!J2:J119,"Pass") -> 0 | E28: =COUNTIFS('Test Cases'!B2:B119,$B28,'Test Cases'!J2:J119,"Fail") -> 0 | F28: =COUNTIFS('Test Cases'!B2:B119,$B28,'Test Cases'!J2:J119,"Not Run") -> 5 | G28: =IFERROR(D28/(D28+E28),0) -> 0
B29: Parent portal & app | C29: =COUNTIF('Test Cases'!B2:B119,$B29) -> 7 | D29: =COUNTIFS('Test Cases'!B2:B119,$B29,'Test Cases'!J2:J119,"Pass") -> 0 | E29: =COUNTIFS('Test Cases'!B2:B119,$B29,'Test Cases'!J2:J119,"Fail") -> 0 | F29: =COUNTIFS('Test Cases'!B2:B119,$B29,'Test Cases'!J2:J119,"Not Run") -> 7 | G29: =IFERROR(D29/(D29+E29),0) -> 0
B30: Teacher portal & app | C30: =COUNTIF('Test Cases'!B2:B119,$B30) -> 5 | D30: =COUNTIFS('Test Cases'!B2:B119,$B30,'Test Cases'!J2:J119,"Pass") -> 0 | E30: =COUNTIFS('Test Cases'!B2:B119,$B30,'Test Cases'!J2:J119,"Fail") -> 0 | F30: =COUNTIFS('Test Cases'!B2:B119,$B30,'Test Cases'!J2:J119,"Not Run") -> 5 | G30: =IFERROR(D30/(D30+E30),0) -> 0
B31: AI knowledge assistant | C31: =COUNTIF('Test Cases'!B2:B119,$B31) -> 4 | D31: =COUNTIFS('Test Cases'!B2:B119,$B31,'Test Cases'!J2:J119,"Pass") -> 0 | E31: =COUNTIFS('Test Cases'!B2:B119,$B31,'Test Cases'!J2:J119,"Fail") -> 0 | F31: =COUNTIFS('Test Cases'!B2:B119,$B31,'Test Cases'!J2:J119,"Not Run") -> 4 | G31: =IFERROR(D31/(D31+E31),0) -> 0
B32: Support ticketing (item 14) | C32: =COUNTIF('Test Cases'!B2:B119,$B32) -> 4 | D32: =COUNTIFS('Test Cases'!B2:B119,$B32,'Test Cases'!J2:J119,"Pass") -> 0 | E32: =COUNTIFS('Test Cases'!B2:B119,$B32,'Test Cases'!J2:J119,"Fail") -> 0 | F32: =COUNTIFS('Test Cases'!B2:B119,$B32,'Test Cases'!J2:J119,"Not Run") -> 4 | G32: =IFERROR(D32/(D32+E32),0) -> 0
B33: Search | C33: =COUNTIF('Test Cases'!B2:B119,$B33) -> 2 | D33: =COUNTIFS('Test Cases'!B2:B119,$B33,'Test Cases'!J2:J119,"Pass") -> 0 | E33: =COUNTIFS('Test Cases'!B2:B119,$B33,'Test Cases'!J2:J119,"Fail") -> 0 | F33: =COUNTIFS('Test Cases'!B2:B119,$B33,'Test Cases'!J2:J119,"Not Run") -> 2 | G33: =IFERROR(D33/(D33+E33),0) -> 0
B34: Security, privacy & audit | C34: =COUNTIF('Test Cases'!B2:B119,$B34) -> 5 | D34: =COUNTIFS('Test Cases'!B2:B119,$B34,'Test Cases'!J2:J119,"Pass") -> 0 | E34: =COUNTIFS('Test Cases'!B2:B119,$B34,'Test Cases'!J2:J119,"Fail") -> 0 | F34: =COUNTIFS('Test Cases'!B2:B119,$B34,'Test Cases'!J2:J119,"Not Run") -> 5 | G34: =IFERROR(D34/(D34+E34),0) -> 0
B35: Mobile applications (cross-cutting) | C35: =COUNTIF('Test Cases'!B2:B119,$B35) -> 5 | D35: =COUNTIFS('Test Cases'!B2:B119,$B35,'Test Cases'!J2:J119,"Pass") -> 0 | E35: =COUNTIFS('Test Cases'!B2:B119,$B35,'Test Cases'!J2:J119,"Fail") -> 0 | F35: =COUNTIFS('Test Cases'!B2:B119,$B35,'Test Cases'!J2:J119,"Not Run") -> 5 | G35: =IFERROR(D35/(D35+E35),0) -> 0
B36: Operations & reporting (Phase 13) | C36: =COUNTIF('Test Cases'!B2:B119,$B36) -> 3 | D36: =COUNTIFS('Test Cases'!B2:B119,$B36,'Test Cases'!J2:J119,"Pass") -> 0 | E36: =COUNTIFS('Test Cases'!B2:B119,$B36,'Test Cases'!J2:J119,"Fail") -> 0 | F36: =COUNTIFS('Test Cases'!B2:B119,$B36,'Test Cases'!J2:J119,"Not Run") -> 3 | G36: =IFERROR(D36/(D36+E36),0) -> 0
B37: TOTAL | C37: =SUM(C16:C36) -> 118 | D37: =SUM(D16:D36) -> 0 | E37: =SUM(E16:E36) -> 0 | F37: =SUM(F16:F36) -> 118 | G37: =IFERROR(D37/(D37+E37),0) -> 0

Sheet Test Cases
A1: Test ID | B1: Area / Module | C1: Portal | D1: Priority | E1: Type | F1: Test Scenario | G1: Preconditions | H1: Test Steps | I1: Expected Result | J1: Status | K1: Actual Result / Notes | L1: Tester | M1: Date Tested
A2: AUTH-01 | B2: Authentication & account security | C2: All / Login | D2: High | E2: Functional | F2: Valid login (school admin) | G2: A school admin account exists | H2: 1. Open the app and go to the login page. 2. Enter a valid school-admin email and password. 3. Submit. | I2: User is authenticated and routed to the school administration portal. | J2: Not Run
A3: AUTH-02 | B3: Authentication & account security | C3: All / Login | D3: High | E3: Functional | F3: Role-based landing routing | G3: Accounts for each role exist | H3: 1. Log in as teacher, then driver, then transport manager, then parent (separately). | I3: Each role lands on its dedicated portal (/teacher, /driver, /transport, /parent) — not a generic page. | J3: Not Run
A4: AUTH-03 | B4: Authentication & account security | C4: All / Login | D4: High | E4: Security | F4: Invalid password rejected | G4: A valid account exists | H4: 1. Enter a valid email with a wrong password. 2. Submit. | I4: Login is rejected with a generic error; no session is created. | J4: Not Run
A5: AUTH-04 | B5: Authentication & account security | C5: All / Login | D5: High | E5: Functional | F5: TOTP multi-factor authentication | G5: MFA enrolled on the account | H5: 1. Log in with email/password. 2. Enter the current TOTP code. | I5: Access granted only after a correct code; an incorrect code is rejected. | J5: Not Run
A6: AUTH-05 | B6: Authentication & account security | C6: All / Login | D6: Medium | E6: Functional | F6: Mandatory MFA enrolment gate | G6: Policy 'MFA required' is on; account has no MFA | H6: 1. Log in with email/password. | I6: Login returns an MFA-enrolment requirement and walks the user through enrolling before entry. | J6: Not Run
A7: AUTH-06 | B7: Authentication & account security | C7: All / Login | D7: Medium | E7: Functional | F7: Password expiry & grace | G7: Password expiry policy configured; password past expiry | H7: 1. Log in with an expired password. | I7: User is prompted to change the password now, with a 'remind me later' option while within the grace period. | J7: Not Run
A8: AUTH-07 | B8: Authentication & account security | C8: All / Login | D8: Medium | E8: Functional | F8: Show/Hide password & keep me logged in | G8: On the login screen | H8: 1. Toggle show/hide on the password field. 2. Tick 'keep me logged in' and log in. | I8: Password value is revealed/hidden on toggle; the extended (30-day) session is issued. | J8: Not Run
A9: AUTH-08 | B9: Authentication & account security | C9: All / Login | D9: High | E9: Security | F9: Sign out everywhere revokes sessions | G9: Logged in on two devices/browsers | H9: 1. On device A, open Security and choose 'sign out everywhere'. 2. Refresh device B. | I9: All other sessions are invalidated; device B must log in again. | J9: Not Run
A10: AUTH-09 | B10: Authentication & account security | C10: All / Login | D10: Medium | E10: Security | F10: Rate limiting on repeated failures | G10: — | H10: 1. Submit many rapid failed logins for one account/IP. | I10: Further attempts are throttled/blocked temporarily. | J10: Not Run
A11: AUTH-10 | B11: Authentication & account security | C11: All / Login | D11: Medium | E11: Security | F11: Disabled/suspended account blocked | G11: A suspended user exists | H11: 1. Attempt to log in as the suspended user. | I11: Login is refused with an appropriate message. | J11: Not Run
A12: RBAC-01 | B12: Roles & Access Management (item 12) | C12: School Admin | D12: High | E12: Functional | F12: View roles & permissions catalogue | G12: Logged in as School Administrator | H12: 1. Go to Settings > Access management > Roles & permissions. | I12: Built-in and custom roles list with grouped feature permissions, page access and CRUD matrices. | J12: Not Run
A13: RBAC-02 | B13: Roles & Access Management (item 12) | C13: School Admin | D13: High | E13: Functional | F13: Create a custom role | G13: Access management open | H13: 1. Create a new role, set a name. 2. Tick a subset of feature permissions and pages. 3. Save. | I13: Role is created and appears in the list; an audit entry (ROLE_CREATED) is written. | J13: Not Run
... A119: OPS-03 | B119: Operations & reporting (Phase 13) | C119: School Admin | D119: Medium | E119: Functional | F119: Scheduled & trust roll-up | G119: A trust/group | H119: 1. Configure a scheduled report; view group roll-up. | I119: Scheduled report configured; trust-level roll-up aggregates member schools. | J119: Not Run
